mbed_tools_ci_scripts/__init__.py
mbed_tools_ci_scripts/_version.py
mbed_tools_ci_scripts/create_news_file.py
mbed_tools_ci_scripts/generate_docs.py
mbed_tools_ci_scripts/generate_news.py
mbed_tools_ci_scripts/get_config.py
mbed_tools_ci_scripts/license_files.py
mbed_tools_ci_scripts/report_third_party_ip.py
mbed_tools_ci_scripts/tag_and_release.py
mbed_tools_ci_scripts/spdx_report/__init__.py
mbed_tools_ci_scripts/spdx_report/spdx_dependency.py
mbed_tools_ci_scripts/spdx_report/spdx_document.py
mbed_tools_ci_scripts/spdx_report/spdx_file.py
mbed_tools_ci_scripts/spdx_report/spdx_helpers.py
mbed_tools_ci_scripts/spdx_report/spdx_package.py
mbed_tools_ci_scripts/spdx_report/spdx_project.py
mbed_tools_ci_scripts/spdx_report/spdx_summary.py
mbed_tools_ci_scripts/spdx_report/templates/third_party_IP_report.csv.jinja2
mbed_tools_ci_scripts/spdx_report/templates/third_party_IP_report.html.jinja2
mbed_tools_ci_scripts/spdx_report/templates/third_party_IP_report.txt.jinja2
mbed_tools_ci_scripts/utils/__init__.py
mbed_tools_ci_scripts/utils/aws_helpers.py
mbed_tools_ci_scripts/utils/configuration.py
mbed_tools_ci_scripts/utils/definitions.py
mbed_tools_ci_scripts/utils/filesystem_helpers.py
mbed_tools_ci_scripts/utils/git_helpers.py
mbed_tools_ci_scripts/utils/hash_helpers.py
mbed_tools_ci_scripts/utils/logging.py
mbed_tools_ci_scripts/utils/package_helpers.py
mbed_tools_ci_scripts/utils/python_helpers.py
mbed_tools_ci_scripts/utils/string_helpers.py
mbed_tools_ci_scripts/utils/third_party_licences.py
mbed_tools_ci_scripts-1.7.5.dist-info/LICENSE
mbed_tools_ci_scripts-1.7.5.dist-info/METADATA
mbed_tools_ci_scripts-1.7.5.dist-info/WHEEL
mbed_tools_ci_scripts-1.7.5.dist-info/entry_points.txt
mbed_tools_ci_scripts-1.7.5.dist-info/top_level.txt
mbed_tools_ci_scripts-1.7.5.dist-info/RECORD
