Metadata-Version: 2.1
Name: mbed-tools-ci-scripts
Version: 1.7.5
Summary: Continuous Integration scripts used by Mbed tools Python packages
Home-page: https://github.com/ARMmbed/mbed-tools-ci-scripts
Author: Mbed team
Author-email: support@mbed.com
License: Apache 2.0
Keywords: Arm Mbed OS MbedOS Tools CI Scripts Automation
Platform: UNKNOWN
Classifier: Development Status :: 4 - Beta
Classifier: Intended Audience :: Developers
Classifier: License :: OSI Approved :: Apache Software License
Classifier: Programming Language :: Python
Classifier: Programming Language :: Python :: 3 :: Only
Classifier: Programming Language :: Python :: 3.6
Classifier: Programming Language :: Python :: 3.7
Classifier: Programming Language :: Python :: 3.8
Classifier: Topic :: Software Development :: Build Tools
Classifier: Topic :: Software Development :: Embedded Systems
Requires-Python: >=3.6,<4
Requires-Dist: gitpython
Requires-Dist: towncrier (==19.2.0)
Requires-Dist: pyautoversion (~=1.2.0)
Requires-Dist: pdoc3
Requires-Dist: toml
Requires-Dist: python-dotenv
Requires-Dist: twine
Requires-Dist: boto3
Requires-Dist: packaging
Requires-Dist: licenseheaders (<0.8.6)
Requires-Dist: spdx-tools
Requires-Dist: license-expression
Requires-Dist: wcmatch
Requires-Dist: jellyfish
Requires-Dist: jinja2
Requires-Dist: dataclasses ; python_version < "3.7"
